deepxube/__init__.py
deepxube/environments/__init__.py
deepxube/environments/cube3.py
deepxube/environments/env_utils.py
deepxube/environments/environment_abstract.py
deepxube/environments/n_puzzle.py
deepxube/environments/sokoban.py
deepxube/logic/__init__.py
deepxube/logic/asp.py
deepxube/logic/logic_objects.py
deepxube/logic/logic_utils.py
deepxube/nnet/__init__.py
deepxube/nnet/nnet_utils.py
deepxube/nnet/pytorch_models.py
deepxube/search/__init__.py
deepxube/search/astar.py
deepxube/search/greedy_policy.py
deepxube/search/search_utils.py
deepxube/specification/__init__.py
deepxube/specification/spec_goal_asp.py
deepxube/tests/__init__.py
deepxube/tests/test_env.py
deepxube/training/__init__.py
deepxube/training/avi.py
deepxube/updaters/__init__.py
deepxube/updaters/updater.py
deepxube/utils/__init__.py
deepxube/utils/data_utils.py
deepxube/utils/misc_utils.py
deepxube/utils/timing_utils.py
deepxube/utils/viz_utils.py
deepxube/visualizers/__init__.py
deepxube/visualizers/cube3_viz_simple.py
deepxube-0.1.6.dist-info/licenses/LICENSE
deepxube-0.1.6.dist-info/METADATA
deepxube-0.1.6.dist-info/WHEEL
deepxube-0.1.6.dist-info/top_level.txt
deepxube-0.1.6.dist-info/RECORD
