Metadata-Version: 2.4
Name: deepxube
Version: 0.1.6
Summary: Solving pathfinding problems in an explainable manner with deep learning, reinforcement learning, heuristic search, and logic
Author-email: Forest Agostinelli <foresta@cse.sc.edu>
Project-URL: Repository, https://github.com/forestagostinelli/DeepXube/
Keywords: DeepXube,DeepCubeA,DeepCube,deep learning,reinforcement learning,search,heuristic search,pathfinding,planning,Rubik's Cube,Sliding Tile Puzzle,Sokoban
Requires-Python: >=3.10
License-File: LICENSE
Requires-Dist: torch>=2.0
Requires-Dist: numpy==1.*
Requires-Dist: matplotlib
Requires-Dist: clingo
Requires-Dist: wget
Requires-Dist: filelock
Requires-Dist: pillow
Requires-Dist: types-Pillow
Requires-Dist: imageio
Provides-Extra: test
Requires-Dist: pytest; extra == "test"
Requires-Dist: pytest-cov; extra == "test"
Requires-Dist: mypy; extra == "test"
Requires-Dist: flake8; extra == "test"
Requires-Dist: tox; extra == "test"
Dynamic: license-file
